dotpup/__init__.py
dotpup/cli.py
dotpup/config.py
dotpup/output.py
dotpup/utils.py
dotpup/commands/__init__.py
dotpup/commands/base.py
dotpup/commands/link.py
dotpup/commands/store.py
dotpup/commands/update.py
dotpup-1.0.1.dist-info/LICENSE
dotpup-1.0.1.dist-info/METADATA
dotpup-1.0.1.dist-info/WHEEL
dotpup-1.0.1.dist-info/entry_points.txt
dotpup-1.0.1.dist-info/top_level.txt
dotpup-1.0.1.dist-info/RECORD
