Metadata-Version: 2.1
Name: dotpup
Version: 1.0.1
Summary: UNKNOWN
Home-page: https://github.com/sztomi/dotpup
Author: UNKNOWN
Author-email: UNKNOWN
License: MIT
Platform: UNKNOWN
